CryptoPad.py
mZipAES.py
CryptoPad-0.8.dist-info/METADATA
CryptoPad-0.8.dist-info/WHEEL
CryptoPad-0.8.dist-info/top_level.txt
CryptoPad-0.8.dist-info/RECORD
