Metadata-Version: 2.1
Name: CryptoPad
Version: 0.8
Summary: A simple notepad supporting ZIP AES-256 encrypted documents, coded in Python
Author-email: maxpat78 <maxpat78@yahoo.it>
License: GPL
Project-URL: homepage, https://github.com/maxpat78/CryptoPad
Project-URL: repository, https://github.com/maxpat78/CryptoPad.git
Keywords: notepad,AES,encryption,text document,editor
Requires-Python: >=3.0
Requires-Dist: pycryptodome
